pyservoce/__init__.py
pyservoce/libservoce.cpython-39-x86_64-linux-gnu.so
pyservoce/libs/libTKBO.so.7
pyservoce/libs/libTKBRep.so.7
pyservoce/libs/libTKBin.so.7
pyservoce/libs/libTKBinL.so.7
pyservoce/libs/libTKBool.so.7
pyservoce/libs/libTKCAF.so.7
pyservoce/libs/libTKCDF.so.7
pyservoce/libs/libTKFillet.so.7
pyservoce/libs/libTKG2d.so.7
pyservoce/libs/libTKG3d.so.7
pyservoce/libs/libTKGeomAlgo.so.7
pyservoce/libs/libTKGeomBase.so.7
pyservoce/libs/libTKHLR.so.7
pyservoce/libs/libTKLCAF.so.7
pyservoce/libs/libTKMath.so.7
pyservoce/libs/libTKMesh.so.7
pyservoce/libs/libTKOffset.so.7
pyservoce/libs/libTKOpenGl.so.7
pyservoce/libs/libTKPrim.so.7
pyservoce/libs/libTKSTL.so.7
pyservoce/libs/libTKService.so.7
pyservoce/libs/libTKShHealing.so.7
pyservoce/libs/libTKTopAlgo.so.7
pyservoce/libs/libTKV3d.so.7
pyservoce/libs/libTKernel.so.7
pyservoce-1.24.0.dist-info/METADATA
pyservoce-1.24.0.dist-info/WHEEL
pyservoce-1.24.0.dist-info/top_level.txt
pyservoce-1.24.0.dist-info/RECORD
