Metadata-Version: 2.1
Name: pyservoce
Version: 1.24.0
Summary: CAD system for righteous zen programmers 
Home-page: https://github.com/mirmik/servoce
Author: mirmik
Author-email: mirmikns@yandex.ru
License: MIT
Keywords: testing,cad
Platform: UNKNOWN
